avatar/__init__.py
avatar/daemon/__init__.py
avatar/daemon/brainbox_service.py
avatar/daemon/chat_service.py
avatar/daemon/image_service.py
avatar/daemon/mock_sound_service.py
avatar/daemon/narration_service.py
avatar/daemon/paraphrase_service.py
avatar/daemon/sound_command_unblocker_service.py
avatar/daemon/speaker_identification_service.py
avatar/daemon/state_to_utterances_application_service.py
avatar/daemon/stt_integration_service.py
avatar/daemon/tts_integration_service.py
avatar/daemon/tts_service.py
avatar/daemon/user_walk_in_service.py
avatar/daemon/volume_control_service.py
avatar/daemon/common/__init__.py
avatar/daemon/common/avatar_service.py
avatar/daemon/common/command_confirmation_queue.py
avatar/daemon/common/state.py
avatar/daemon/common/world.py
avatar/daemon/common/content_manager/__init__.py
avatar/daemon/common/content_manager/content_manager.py
avatar/daemon/common/content_manager/data_providers.py
avatar/daemon/common/content_manager/feedback_provider.py
avatar/daemon/common/content_manager/media_library_manager.py
avatar/daemon/common/content_manager/strategies.py
avatar/daemon/common/content_manager/tag_matcher.py
avatar/daemon/common/known_messages/__init__.py
avatar/daemon/common/known_messages/backend_messages.py
avatar/daemon/common/known_messages/buttons.py
avatar/daemon/common/known_messages/console_messages.py
avatar/daemon/common/known_messages/misc.py
avatar/daemon/common/known_messages/text_messages.py
avatar/daemon/common/vector_identificator/__init__.py
avatar/daemon/common/vector_identificator/straregies.py
avatar/daemon/common/vector_identificator/vector_identificator.py
avatar/daemon/stt_service/__init__.py
avatar/daemon/stt_service/stt_service.py
avatar/daemon/stt_service/rhasspy_training/__init__.py
avatar/daemon/stt_service/rhasspy_training/intents_pack.py
avatar/daemon/stt_service/rhasspy_training/kaldi_grammar_builder.py
avatar/daemon/stt_service/rhasspy_training/rhasspy_handler.py
kaia_avatar-4.0.9.dist-info/METADATA
kaia_avatar-4.0.9.dist-info/WHEEL
kaia_avatar-4.0.9.dist-info/top_level.txt
kaia_avatar-4.0.9.dist-info/RECORD
